container_detect/__init__.py
container_detect/core.py
container_detect/py.typed
container_detect-1.0.0.dist-info/METADATA
container_detect-1.0.0.dist-info/WHEEL
container_detect-1.0.0.dist-info/licenses/LICENSE
container_detect-1.0.0.dist-info/RECORD
