Metadata-Version: 2.4
Name: container-detect
Version: 1.0.0
Summary: Detect if your Python process is running inside a container. Supports Docker, Podman, Kubernetes, containerd, LXC, and more. Inspired by the popular is-inside-container npm package. Supports cached results with optional refresh.
Project-URL: Homepage, https://github.com/ysskrishna/container-detect
Project-URL: Repository, https://github.com/ysskrishna/container-detect.git
Project-URL: Issues, https://github.com/ysskrishna/container-detect/issues
Project-URL: Changelog, https://github.com/ysskrishna/container-detect/blob/main/CHANGELOG.md
Project-URL: Discussions, https://github.com/ysskrishna/container-detect/discussions
Author-email: "Y. Siva Sai Krishna" <sivasaikrishnassk@gmail.com>
License: MIT
License-File: LICENSE
Keywords: container,container-detection,containerd,containerized,detect,detection,docker,environment,inside,is-inside-container,kubernetes,lxc,mit license,podman,process,utilities,utils,ysskrishna
Classifier: Development Status :: 5 - Production/Stable
Classifier: Intended Audience :: Developers
Classifier: License :: OSI Approved :: MIT License
Classifier: Operating System :: POSIX :: Linux
Classifier: Programming Language :: Python :: 3
Classifier: Programming Language :: Python :: 3.8
Classifier: Programming Language :: Python :: 3.9
Classifier: Programming Language :: Python :: 3.10
Classifier: Programming Language :: Python :: 3.11
Classifier: Programming Language :: Python :: 3.12
Classifier: Topic :: Software Development :: Libraries :: Python Modules
Classifier: Topic :: System :: Systems Administration
Classifier: Topic :: Utilities
Classifier: Typing :: Typed
Requires-Python: >=3.8
